setup.py
lunardate/__init__.py
pylunardate.egg-info/PKG-INFO
pylunardate.egg-info/SOURCES.txt
pylunardate.egg-info/dependency_links.txt
pylunardate.egg-info/top_level.txt