Metadata-Version: 1.1
Name: pylunardate
Version: 0.0.3
Summary: A Korean Calendar Library in Pure Python
Home-page: https://github.com/charsyam/pylunardate
Author: charsyam
Author-email: charsyam@gmail.com
License: BSD
Platform: UNKNOWN
Classifier: Development Status :: 4 - Beta
Classifier: Programming Language :: Python
Classifier: License :: OSI Approved :: BSD License
Classifier: Operating System :: OS Independent
Classifier: Programming Language :: Python
Classifier: Programming Language :: Python :: 3
Classifier: Topic :: Software Development :: Libraries
